geode_numerics/__init__.py
geode_numerics/__init__.pyi
geode_numerics/core_numerics.py
geode_numerics/core_numerics.pyi
geode_numerics/frame_field.py
geode_numerics/frame_field.pyi
geode_numerics/py.typed
geode_numerics/scalar_function.py
geode_numerics/scalar_function.pyi
geode_numerics/surface_numerics.py
geode_numerics/surface_numerics.pyi
geode_numerics/lib64/__init__.pyi
geode_numerics/lib64/geode_numerics_py_core.cpython-311-x86_64-linux-gnu.so
geode_numerics/lib64/geode_numerics_py_core.pyi
geode_numerics/lib64/geode_numerics_py_frame_field.cpython-311-x86_64-linux-gnu.so
geode_numerics/lib64/geode_numerics_py_frame_field.pyi
geode_numerics/lib64/geode_numerics_py_scalar_function.cpython-311-x86_64-linux-gnu.so
geode_numerics/lib64/geode_numerics_py_scalar_function.pyi
geode_numerics/lib64/geode_numerics_py_surface.cpython-311-x86_64-linux-gnu.so
geode_numerics/lib64/geode_numerics_py_surface.pyi
geode_numerics/lib64/libGeode-Numerics_core.so
geode_numerics/lib64/libGeode-Numerics_frame_field.so
geode_numerics/lib64/libGeode-Numerics_scalar_function.so
geode_numerics/lib64/libGeode-Numerics_surface.so
geode_numerics-6.4.9.dist-info/METADATA
geode_numerics-6.4.9.dist-info/WHEEL
geode_numerics-6.4.9.dist-info/top_level.txt
geode_numerics-6.4.9.dist-info/RECORD
