Metadata-Version: 2.4
Name: Geode-Numerics
Version: 6.4.9
Summary: Numerical algorithm module
Author-email: Geode-solutions <contact@geode-solutions.com>
License: Proprietary
Requires-Python: <3.13,>=3.9
Requires-Dist: geode-common==33.*,>=33.14.4
Requires-Dist: opengeode-core==15.*,>=15.30.10
